geom/__init__.py
geom/circle.py
geom/rectangle.py
nel_calculations-0.1.dist-info/METADATA
nel_calculations-0.1.dist-info/WHEEL
nel_calculations-0.1.dist-info/top_level.txt
nel_calculations-0.1.dist-info/RECORD
