Metadata-Version: 2.1
Name: nel_calculations
Version: 0.1
Summary: A simple python library for calculating area of shapes
Author: Abdul Nelfrank
